spexread/__init__.py
spexread/_version.py
spexread/data_models.py
spexread/parsing.py
spexread/structdef.py
spexread/transformation.py
spexread-0.2.1.dist-info/METADATA
spexread-0.2.1.dist-info/WHEEL
spexread-0.2.1.dist-info/licenses/LICENSE
spexread-0.2.1.dist-info/RECORD
