Metadata-Version: 2.4
Name: spexread
Version: 0.2.1
Summary: A module for reading Princeton Instruments SPE files (version 2.x and 3.0) captured by WinSpec or LightField
Project-URL: Documentation, https://github.com/AntoineTUE/spexread
Project-URL: Source, https://github.com/AntoineTUE/spexread
Author-email: Antoine Salden <t.p.w.salden@tue.nl>
License: MIT
License-File: LICENSE
Keywords: Lightfield,Princeton Instruments,WinSpec,file-reader,imaging,research,science,spectroscopy
Classifier: Development Status :: 4 - Beta
Classifier: Framework :: Pydantic :: 2
Classifier: Intended Audience :: Science/Research
Classifier: License :: OSI Approved :: MIT License
Classifier: Programming Language :: Python
Classifier: Programming Language :: Python :: 3.10
Classifier: Programming Language :: Python :: 3.11
Classifier: Programming Language :: Python :: 3.12
Classifier: Programming Language :: Python :: 3.13
Classifier: Programming Language :: Python :: 3.14
Classifier: Programming Language :: Python :: Implementation :: CPython
Classifier: Topic :: Scientific/Engineering :: Chemistry
Classifier: Topic :: Scientific/Engineering :: Physics
Requires-Python: >=3.10
Requires-Dist: lxml>=4.0
Requires-Dist: numpy>=2.1
Requires-Dist: numpydantic>=1.6
Requires-Dist: pydantic>=2.7
Requires-Dist: xarray>=2024.09.0
Provides-Extra: docs
Requires-Dist: mkdocs-api-autonav; extra == 'docs'
Requires-Dist: mkdocs-git-revision-date-localized-plugin; extra == 'docs'
Requires-Dist: mkdocs-github-admonitions-plugin; extra == 'docs'
Requires-Dist: mkdocs-include-markdown-plugin; extra == 'docs'
Requires-Dist: mkdocs-jupyter; extra == 'docs'
Requires-Dist: mkdocs-material==9.7.0; extra == 'docs'
Requires-Dist: mkdocs-section-index; extra == 'docs'
Requires-Dist: mkdocstrings; extra == 'docs'
Requires-Dist: mkdocstrings-python; extra == 'docs'
Requires-Dist: mkdocstrings-python-xref; extra == 'docs'
Requires-Dist: pygments; extra == 'docs'
Requires-Dist: ruff>=0.14.2; extra == 'docs'
